pyramid_capstone/__init__.py
pyramid_capstone/context.py
pyramid_capstone/decorators.py
pyramid_capstone/exceptions.py
pyramid_capstone/handler.py
pyramid_capstone/inspection.py
pyramid_capstone/schema_generator.py
pyramid_capstone/service_builder.py
pyramid_capstone-0.1.2.dist-info/METADATA
pyramid_capstone-0.1.2.dist-info/WHEEL
pyramid_capstone-0.1.2.dist-info/licenses/LICENSE
pyramid_capstone-0.1.2.dist-info/RECORD
