Metadata-Version: 2.4
Name: pyramid_capstone
Version: 0.1.2
Summary: FastAPI-like decorators for Pyramid - Build type-safe REST APIs with automatic validation, serialization, and OpenAPI documentation.
License-File: LICENSE
Author: Robbin dev team
Author-email: fdev@robbin.com.br
Requires-Python: >=3.10,<4.0
Classifier: Programming Language :: Python :: 3
Classifier: Programming Language :: Python :: 3.10
Classifier: Programming Language :: Python :: 3.11
Classifier: Programming Language :: Python :: 3.12
Classifier: Programming Language :: Python :: 3.13
Classifier: Programming Language :: Python :: 3.14
Requires-Dist: cornice (>=6.0,<7.0)
Requires-Dist: marshmallow (>=3.19,<4.0)
Requires-Dist: pycornmarsh
Requires-Dist: pyramid (>=2.0,<3.0)
Requires-Dist: venusian (>=3.0,<4.0)
Project-URL: Documentation, https://tomas_correa.github.io/pyramid-capstone/
Project-URL: Repository, https://github.com/tomas_correa/pyramid-capstone
